README.txt
setup.py
microsaa/__init__.py
microsaa/cellspat.py
microsaa/fibseg.py
microsaa/fibspat.py
microsaa/visual.py
microsaa.egg-info/PKG-INFO
microsaa.egg-info/SOURCES.txt
microsaa.egg-info/dependency_links.txt
microsaa.egg-info/requires.txt
microsaa.egg-info/top_level.txt