Metadata-Version: 2.1
Name: microsaa
Version: 0.0.2
Summary: Tissue Image Analysis
Home-page: UNKNOWN
Author: Georgii Vasiukov
Author-email: <vasyukov.georgiy.yu@gmail.com>
License: UNKNOWN
Keywords: python,spatial,collagen,cells ,integrated
Platform: UNKNOWN
Classifier: Development Status :: 3 - Alpha
Classifier: Intended Audience :: Science/Research
Classifier: Programming Language :: Python :: 3
Classifier: Operating System :: Unix
Classifier: Operating System :: MacOS :: MacOS X
Classifier: Operating System :: Microsoft :: Windows
